pylettes/__init__.py
pylettes/_version.py
pylettes/base.py
pylettes/categorical.py
pylettes/sequential.py
pylettes/utils.py
pylettes-0.2.0.dist-info/LICENSE
pylettes-0.2.0.dist-info/METADATA
pylettes-0.2.0.dist-info/WHEEL
pylettes-0.2.0.dist-info/top_level.txt
pylettes-0.2.0.dist-info/RECORD
