Metadata-Version: 2.1
Name: pylettes
Version: 0.2.0
Summary: Beautiful palettes in Python
Home-page: https://github.com/fcomitani/pylettes
Download-URL: https://github.com/fcomitani/pylettes/archive/0.2.0.tar.gz
Author: Federico Comitani
Author-email: federico.comitani@gmail.com
License: GPL-3.0
Keywords: palette,plotting,plots,color
Classifier: Development Status :: 4 - Beta
Classifier: Intended Audience :: Science/Research
Classifier: Topic :: Scientific/Engineering
Classifier: License :: OSI Approved :: GNU General Public License v3 (GPLv3)
Classifier: Programming Language :: Python
Classifier: Programming Language :: Python :: 3
Classifier: Programming Language :: Python :: 3.8
License-File: LICENSE
Requires-Dist: matplotlib (>=1.3.1)
